oceanbase_py/__init__.py
oceanbase_py/sqlalchemy/__init__.py
oceanbase_py/sqlalchemy/datatype.py
oceanbase_py/sqlalchemy/dialect.py
oceanbase_py-0.0.1.2.dist-info/LICENSE.txt
oceanbase_py-0.0.1.2.dist-info/METADATA
oceanbase_py-0.0.1.2.dist-info/WHEEL
oceanbase_py-0.0.1.2.dist-info/entry_points.txt
oceanbase_py-0.0.1.2.dist-info/top_level.txt
oceanbase_py-0.0.1.2.dist-info/RECORD
