Metadata-Version: 2.1
Name: oceanbase-py
Version: 0.0.1.2
Summary: OceanBase sqlalchemy dialect
Home-page: https://www.oceanbase.com/
Author: yuanoOo
Author-email: yuanoOo@gmail.com
License: Apache 2.0
Classifier: Development Status :: 5 - Production/Stable
Classifier: Environment :: Console
Classifier: Intended Audience :: Developers
Classifier: License :: OSI Approved :: Apache Software License
Classifier: Programming Language :: Python
Classifier: Programming Language :: Python :: 3
Classifier: Programming Language :: Python :: Implementation :: CPython
Classifier: Programming Language :: Python :: Implementation :: PyPy
Classifier: Topic :: Database :: Front-Ends
License-File: LICENSE.txt
Requires-Dist: sqlalchemy <2,>=1.4
Requires-Dist: sqlalchemy-utils <0.39,>=0.38.3
Requires-Dist: mysqlclient <3,>=2.1.0
